Metadata-Version: 2.4
Name: FastAPIBig
Version: 0.1.3
Requires-Dist: Click
Requires-Dist: FastAPI
Requires-Dist: pydantic
Requires-Dist: SQLAlchemy
Requires-Dist: uvicorn
Requires-Dist: asyncpg
Requires-Dist: psycopg-binary
Requires-Dist: aiosqlite
